tzview/__init__.py
tzview/__main__.py
tzview/app.py
tzview-0.3.dist-info/LICENSE.md
tzview-0.3.dist-info/METADATA
tzview-0.3.dist-info/WHEEL
tzview-0.3.dist-info/top_level.txt
tzview-0.3.dist-info/RECORD
