Metadata-Version: 2.1
Name: tzview
Version: 0.3
Summary: View datetime in different time zones.
Home-page: https://github.com/ju-sh/tzview
Author: Julin S
Author-email: 
License: UNKNOWN
Project-URL: Changelog, https://github.com/ju-sh/tzview/CHANGELOG.md
Project-URL: Issue Tracker, https://github.com/ju-sh/tzview/issues
Platform: UNKNOWN
Classifier: Programming Language :: Python :: 3
Classifier: License :: OSI Approved :: MIT License
Classifier: Operating System :: OS Independent
Classifier: Topic :: Utilities
Classifier: Development Status :: 2 - Pre-Alpha
Classifier: Natural Language :: English
Requires-Python: >=3.6
Requires-Dist: python-dateutil
Requires-Dist: pytz
Requires-Dist: tzcity
Requires-Dist: tzlocal
